aiotelegraph/__init__.py
aiotelegraph/client.py
aiotelegraph/entities.py
aiotelegraph/exceptions.py
aiotelegraph-0.1.0.dist-info/LICENSE
aiotelegraph-0.1.0.dist-info/METADATA
aiotelegraph-0.1.0.dist-info/WHEEL
aiotelegraph-0.1.0.dist-info/top_level.txt
aiotelegraph-0.1.0.dist-info/RECORD
