Metadata-Version: 2.1
Name: aiotelegraph
Version: 0.1.0
Summary: UNKNOWN
Home-page: https://github.com/OlegYurchik/aiotelegraph
Author: Oleg Yurchik
Author-email: oleg.yurchik@protonmail.com
License: UNKNOWN
Platform: UNKNOWN
Requires-Dist: aiohttp
